falcon_python-0.1.0.dist-info/METADATA
falcon_python-0.1.0.dist-info/WHEEL
falcon_python/__init__.py
falcon_python/__init__.pyi
falcon_python/py.typed
falcon_python/falcon_python.cpython-312-x86_64-linux-gnu.so
falcon_python-0.1.0.dist-info/RECORD
