Metadata-Version: 2.4
Name: falcon_python
Version: 0.1.0
